CHANGES.txt
DEPENDENCES.txt
README.txt
setup.py
src/ng/__init__.py
src/ng.base.itemsfilter.egg-info/PKG-INFO
src/ng.base.itemsfilter.egg-info/SOURCES.txt
src/ng.base.itemsfilter.egg-info/dependency_links.txt
src/ng.base.itemsfilter.egg-info/namespace_packages.txt
src/ng.base.itemsfilter.egg-info/not-zip-safe
src/ng.base.itemsfilter.egg-info/requires.txt
src/ng.base.itemsfilter.egg-info/top_level.txt
src/ng/base/__init__.py
src/ng/base/itemsfilter/__init__.py
src/ng/base/itemsfilter/configure.zcml
src/ng/base/itemsfilter/interfaces.py
src/ng/base/itemsfilter/itemsfilter.py
src/ng/base/itemsfilter/itemsfiltercondition.py
src/ng/base/itemsfilter/itemsfilterrecord.py
src/ng/base/itemsfilter/ng.base.itemsfilter.txt
src/ng/base/itemsfilter/etc/ng.base.itemsfilter-configure.zcml