Metadata-Version: 1.0
Name: ng.base.itemsfilter
Version: 0.0.2
Summary: Base class used to create adapters to filter container items by some conditions and to cache result
Home-page: http://www.dreambot.ru/product/DreamBotZope3Releases/ng.base.itemsfilter
Author: Andrey Orlov
Author-email: dbdt@dreambot.ru
License: GPL v2.1
Platform: UNKNOWN
Classifier: Environment :: Web Environment
Classifier: Intended Audience :: Developers
Classifier: License :: OSI Approved :: GNU General Public License (GPL)
Classifier: Programming Language :: Python
Classifier: Operating System :: OS Independent
Classifier: Topic :: Internet :: WWW/HTTP
Classifier: Framework :: Zope3
